grades_check/__init__.py
grades_check/cli.py
grades_check/grades_check.py
grades_check2-0.2.0.dist-info/AUTHORS.rst
grades_check2-0.2.0.dist-info/LICENSE
grades_check2-0.2.0.dist-info/METADATA
grades_check2-0.2.0.dist-info/WHEEL
grades_check2-0.2.0.dist-info/entry_points.txt
grades_check2-0.2.0.dist-info/top_level.txt
grades_check2-0.2.0.dist-info/RECORD
